radshap/__init__.py
radshap/_aggregator.py
radshap/_masking.py
radshap/_utils.py
radshap/plot.py
radshap/shapley.py
tests/__init__.py
radshap-0.0.1.dist-info/LICENSE.md
radshap-0.0.1.dist-info/METADATA
radshap-0.0.1.dist-info/WHEEL
radshap-0.0.1.dist-info/top_level.txt
radshap-0.0.1.dist-info/RECORD
