Metadata-Version: 2.1
Name: radshap
Version: 0.0.1
Summary: Shapley values for interpreting radiomic models
Home-page: https://github.com/ncaptier/radshap
Author: Nicolas Captier
Author-email: nicolas.captier@curie.fr
License: UNKNOWN
Platform: UNKNOWN
Classifier: Programming Language :: Python :: 3
Classifier: Programming Language :: Python :: 3.7
Classifier: Programming Language :: Python :: 3.8
Classifier: Programming Language :: Python :: 3.9
Classifier: Programming Language :: Python :: 3.10
Classifier: Intended Audience :: Healthcare Industry
Classifier: Intended Audience :: Science/Research
Classifier: Operating System :: OS Independent
Classifier: Topic :: Scientific/Engineering :: Artificial Intelligence
Requires-Python: >=3.7
License-File: LICENSE.md
Requires-Dist: matplotlib
Requires-Dist: numpy
Requires-Dist: joblib >=1.1.0
Requires-Dist: pandas >=1.3.5
Requires-Dist: seaborn >=0.11.2
Requires-Dist: SimpleITK >=1.2.4
Provides-Extra: dev
Requires-Dist: pytest ; extra == 'dev'
Provides-Extra: docs
Requires-Dist: sphinx ==5.3.0 ; extra == 'docs'
Requires-Dist: sphinx-gallery ==0.14.0 ; extra == 'docs'
Requires-Dist: numpydoc ==1.5.0 ; extra == 'docs'
Requires-Dist: nbsphinx ==0.9.3 ; extra == 'docs'
Requires-Dist: ipython ==7.34.0 ; extra == 'docs'
Requires-Dist: sphinx-rtd-theme ==1.3.0 ; extra == 'docs'
